calculations.pyd
mspy/blocks.py
mspy/calculations.c
mspy/calculations.pyd
mspy/mod_basics.py
mspy/mod_calibration.py
mspy/mod_envfit.py
mspy/mod_formulator.py
mspy/mod_mascot.py
mspy/mod_pattern.py
mspy/mod_peakpicking.py
mspy/mod_proteo.py
mspy/mod_signal.py
mspy/mod_stopper.py
mspy/mod_utils.py
mspy/obj_compound.py
mspy/obj_peak.py
mspy/obj_peaklist.py
mspy/obj_scan.py
mspy/obj_sequence.py
mspy/parser_fasta.py
mspy/parser_mgf.py
mspy/parser_mzdata.py
mspy/parser_mzml.py
mspy/parser_mzxml.py
mspy/parser_xy.py
mspy/plot.py
mspy/plot_canvas.py
mspy/plot_objects.py
mspy/__init__.py
mspy-1.1.1.dist-info/DESCRIPTION.rst
mspy-1.1.1.dist-info/METADATA
mspy-1.1.1.dist-info/metadata.json
mspy-1.1.1.dist-info/RECORD
mspy-1.1.1.dist-info/top_level.txt
mspy-1.1.1.dist-info/WHEEL
