Metadata-Version: 2.0
Name: mspy
Version: 1.1.1
Summary: fork of the mMass library mspy http://www.mmass.org/
Home-page: https://github.com/wolski/mspy
Author: Witold Wolski
Author-email: wewolski@gmail.com
License: GPL
Platform: UNKNOWN
Requires-Dist: numpy
